textprompts/__init__.py
textprompts/__main__.py
textprompts/_parser.py
textprompts/cli.py
textprompts/config.py
textprompts/errors.py
textprompts/loaders.py
textprompts/models.py
textprompts/placeholder_utils.py
textprompts/prompt_string.py
textprompts/py.typed
textprompts/safe_string.py
textprompts/savers.py
textprompts-1.1.0.dist-info/WHEEL
textprompts-1.1.0.dist-info/entry_points.txt
textprompts-1.1.0.dist-info/METADATA
textprompts-1.1.0.dist-info/RECORD
