Metadata-Version: 2.4
Name: textprompts
Version: 1.1.0
Summary: Minimal text-based prompt-loader with TOML front-matter
Keywords: prompts,toml,frontmatter,template
Author: Jan Siml
Author-email: Jan Siml <49557684+svilupp@users.noreply.github.com>
License-Expression: MIT
Classifier: Development Status :: 3 - Alpha
Classifier: Intended Audience :: Developers
Classifier: License :: OSI Approved :: MIT License
Classifier: Programming Language :: Python :: 3
Classifier: Programming Language :: Python :: 3.11
Classifier: Programming Language :: Python :: 3.12
Classifier: Programming Language :: Python :: 3.13
Classifier: Topic :: Software Development :: Libraries :: Python Modules
Requires-Dist: pydantic~=2.7
Requires-Dist: tomli>=1.0.0 ; python_full_version < '3.11'
Requires-Python: >=3.11
Project-URL: Bug Tracker, https://github.com/svilupp/textprompts/issues
Project-URL: Documentation, https://github.com/svilupp/textprompts#readme
Project-URL: Homepage, https://github.com/svilupp/textprompts
